pyroll/karman_force_torque/__init__.py
pyroll/karman_force_torque/karman_solver.py
pyroll/karman_force_torque/report.py
pyroll/karman_force_torque/roll_pass.py
pyroll_karman_force_torque-3.0.0a1.dist-info/METADATA
pyroll_karman_force_torque-3.0.0a1.dist-info/WHEEL
pyroll_karman_force_torque-3.0.0a1.dist-info/licenses/LICENSE
pyroll_karman_force_torque-3.0.0a1.dist-info/RECORD
