Metadata-Version: 2.4
Name: pyroll-karman-force-torque
Version: 3.0.0a1
Summary: Plugin for PyRoll providing the power and labour model solving the von-Karman equation.
Author-email: Christoph Renzing <christoph.renzing@imf.tu-freiberg.de>
License-Expression: BSD-3-Clause
License-File: LICENSE
Classifier: Intended Audience :: Manufacturing
Classifier: Intended Audience :: Science/Research
Classifier: Operating System :: OS Independent
Classifier: Topic :: Scientific/Engineering
Requires-Python: <4.0,>=3.9
Requires-Dist: numdifftools
Requires-Dist: pandas~=2.0
Requires-Dist: pyroll-core
